langchain_tools/__init__.py
langchain_tools/retriever/LangChainRetriever.py
langchain_tools/retriever/LangChainRetriever1 copy.py
langchain_tools/retriever/LangChainRetriever2.py
langchain_tools/retriever/__init__.py
langchain_tools/retriever/md/__init__.py
langchain_tools/retriever/md/split_md.py
langchain_tools/router/LangGraphRouter.py
langchain_tools/router/__init__.py
langchain_tools-0.1.34.dist-info/METADATA
langchain_tools-0.1.34.dist-info/WHEEL
langchain_tools-0.1.34.dist-info/top_level.txt
langchain_tools-0.1.34.dist-info/RECORD
